jinjyaml/__init__.py
jinjyaml/_version.py
jinjyaml/constructor.py
jinjyaml/data.py
jinjyaml/functions.py
jinjyaml/py.typed
jinjyaml/representer.py
jinjyaml-0.4.dist-info/AUTHORS.md
jinjyaml-0.4.dist-info/LICENSE
jinjyaml-0.4.dist-info/METADATA
jinjyaml-0.4.dist-info/WHEEL
jinjyaml-0.4.dist-info/top_level.txt
jinjyaml-0.4.dist-info/RECORD
