Metadata-Version: 2.1
Name: jinjyaml
Version: 0.4
Summary: Application specific YAML tag of Jinja2 template
Author-email: liu xue yan <liu_xue_yan@foxmail.com>
License: BSD-3-Clause
Project-URL: homepage, https://pypi.org/project/jinjyaml/
Project-URL: documentation, https://jinjyaml.readthedocs.io/
Project-URL: repository, https://github.com/tanbro/jinjyaml
Project-URL: changelog, https://github.com/tanbro/jinjyaml/blob/master/CHANGELOG.md
Keywords: jinja,jinja2,template,template-engine,yaml,yml,yaml-tag,PyYAML
Classifier: License :: OSI Approved :: BSD License
Classifier: Development Status :: 5 - Production/Stable
Classifier: Intended Audience :: Developers
Classifier: Operating System :: OS Independent
Classifier: Topic :: Software Development :: Libraries :: Python Modules
Classifier: Topic :: Text Processing :: Markup
Classifier: Programming Language :: Python
Classifier: Programming Language :: Python :: 3
Classifier: Programming Language :: Python :: 3.7
Classifier: Programming Language :: Python :: 3.8
Classifier: Programming Language :: Python :: 3.9
Classifier: Programming Language :: Python :: 3.10
Classifier: Programming Language :: Python :: 3.11
Classifier: Programming Language :: Python :: 3.12
Classifier: Programming Language :: Python :: 3.13
Requires-Python: >=3.7
License-File: LICENSE
License-File: AUTHORS.md
Requires-Dist: Jinja2 <4.0,>=3.0
Requires-Dist: PyYAML <7.0,>=5.0
Requires-Dist: typing-extensions ; python_version < "3.11"
